{
  "type": "Tab",
  "id": "basic",
  "title": "{{tab.basic}}",
  "children": [
    {
      "type": "ScrollArea",
      "axis": "vertical",
      "max_height": 600,
      "children": [
        {
          "type": "Column",
          "gap": 10,
          "padding": 16,
          "children": [
            {
              "type": "Label",
              "text": "{{label.basic_title}}",
              "size": 35,
              "bold": true
            },
            {
              "type": "Label",
              "text": "{{label.variants}}",
              "size": 25,
              "color": "#888888"
            },
            {
              "type": "Label",
              "text": "{{label.simple_text}}",
              "size": 14
            },
            {
              "type": "Label",
              "text": "{{label.colored_text}}",
              "size": 14,
              "color": "#66CCFF"
            },
            {
              "type": "Label",
              "text": "{{label.bold_text}}",
              "size": 14,
              "bold": true
            },
            {
              "type": "Label",
              "text": "{{label.italic_text}}",
              "size": 14,
              "italic": true
            },
            {
              "type": "Label",
              "text": "{{label.mono_text}}",
              "size": 13,
              "monospace": true
            },
            {
              "type": "Separator",
              "space": 10
            },
            {
              "type": "Label",
              "text": "{{label.buttons}}",
              "size": 13,
              "color": "#888888"
            },
            {
              "type": "Row",
              "gap": 8,
              "align": "center",
              "children": [
                {
                  "type": "Button",
                  "icon": "floppy-disk",
                  "text": "{{btn.primary}}",
                  "action": "click",
                  "target": "primary",
                  "background": "#3366CC",
                  "tooltip": "{{tooltip.primary}}"
                },
                {
                  "type": "Button",
                  "icon": "x-circle",
                  "text": "{{btn.danger}}",
                  "action": "click",
                  "target": "danger",
                  "background": "#CC3333",
                  "tooltip": "{{tooltip.danger}}"
                },
                {
                  "type": "Button",
                  "icon": "check",
                  "text": "{{btn.success}}",
                  "action": "click",
                  "target": "success",
                  "background": "#00AA66",
                  "tooltip": "{{tooltip.success}}"
                }
               ]
           },
           {
          "type": "Row",
          "gap": 8,
          "align": "center",
          "children": [
            {
              "type": "Button",
              "text": "РџРѕ С†РµРЅС‚СЂСѓ",
              "action": "click",
              "target": "align_center",
              "background": "#555566"
            },
            {
              "type": "Button",
              "text": "РЎР»РµРІР°",
              "action": "click",
              "target": "align_left",
              "background": "#555566",
              "align": "left"
            },
            {
              "type": "Button",
              "text": "РЎРїСЂР°РІР°",
              "action": "click",
              "target": "align_right",
              "background": "#555566",
              "align": "right"
            }
          ]
        },
        {
          "type": "Row",
          "gap": 8,
          "align": "center",
              "children": [
                {
                  "type": "Button",
                  "text": "{{btn.default}}",
                  "action": "click",
                  "target": "default"
                },
                {
                  "type": "Button",
                  "text": "{{btn.disabled}}",
                  "enabled": false,
                  "tooltip": "{{tooltip.disabled}}"
                },
                {
                  "type": "Button",
                  "icon": "floppy-disk"
                },
                {
                  "type": "IconButton",
                  "icon": "floppy-disk",
                  "tooltip": "IconButton test"
                }
              ]
            },
            {
              "type": "Separator",
              "space": 10
            },
            {
              "type": "Label",
              "text": "{{label.switches}}",
              "size": 13,
              "color": "#888888"
            },
            {
              "type": "Checkbox",
              "binding": "use_gpu",
              "text": "{{chk.gpu}}"
            },
            {
              "type": "Checkbox",
              "binding": "auto_start",
              "text": "{{chk.auto_start}}"
            },
            {
              "type": "Separator",
              "space": 10
            },
            {
              "type": "Label",
              "text": "РўРµРјР° (RadioGroup):",
              "size": 13,
              "color": "#888888"
            },
            {
              "type": "RadioGroup",
              "binding": "app_theme",
              "options": [
                {"value": 0, "text": "{{radio.dark}}"},
                {"value": 1, "text": "{{radio.light}}"},
                {"value": 2, "text": "{{radio.auto}}"}
              ]
            }
          ]
        }
      ]
    }
  ]
}